mcdstate/__init__.py
mcdstate/mcd_state.py
mcd_state_client-0.0.0.dist-info/LICENSE
mcd_state_client-0.0.0.dist-info/METADATA
mcd_state_client-0.0.0.dist-info/WHEEL
mcd_state_client-0.0.0.dist-info/top_level.txt
mcd_state_client-0.0.0.dist-info/RECORD
